django_viewsets-0.3.0.dist-info/licenses/LICENSE
viewsets/__init__.py
viewsets/base.py
viewsets/model.py
viewsets/patterns.py
django_viewsets-0.3.0.dist-info/METADATA
django_viewsets-0.3.0.dist-info/WHEEL
django_viewsets-0.3.0.dist-info/top_level.txt
django_viewsets-0.3.0.dist-info/RECORD
