Metadata-Version: 2.4
Name: django-viewsets
Version: 0.3.0
Summary: Avoid boring views and urls.
Author-email: Bertrand Bordage <bordage.bertrand@gmail.com>
License-Expression: BSD-2-Clause
Project-URL: Repository, https://github.com/BertrandBordage/django-viewsets
Classifier: Development Status :: 3 - Alpha
Classifier: Environment :: Web Environment
Classifier: Framework :: Django
Classifier: Intended Audience :: Developers
Classifier: Operating System :: OS Independent
Classifier: Programming Language :: Python
Classifier: Topic :: Internet :: WWW/HTTP :: Dynamic Content
Requires-Python: >=3.4
License-File: LICENSE
Requires-Dist: django>=2.0
Dynamic: license-file
